file_to_base64/__init__.py
file_to_base64/__main__.py
file_to_base64/server.py
mcp_file_to_base64-0.1.1.dist-info/METADATA
mcp_file_to_base64-0.1.1.dist-info/WHEEL
mcp_file_to_base64-0.1.1.dist-info/entry_points.txt
mcp_file_to_base64-0.1.1.dist-info/top_level.txt
mcp_file_to_base64-0.1.1.dist-info/RECORD
