Metadata-Version: 2.4
Name: mcp_file_to_base64
Version: 0.1.1
Summary: Convert the content of a local file to base64 code
Requires-Python: >=3.11
Requires-Dist: click>=8.2.1
Requires-Dist: httpx>=0.28.1
Requires-Dist: mcp>=1.9.2
Requires-Dist: starlette>=0.47.0
